followthemoney_enrich/__init__.py
followthemoney_enrich/aleph.py
followthemoney_enrich/cache.py
followthemoney_enrich/cli.py
followthemoney_enrich/enricher.py
followthemoney_enrich/opencorporates.py
followthemoney_enrich-2.9.7.dist-info/LICENSE
followthemoney_enrich-2.9.7.dist-info/METADATA
followthemoney_enrich-2.9.7.dist-info/WHEEL
followthemoney_enrich-2.9.7.dist-info/entry_points.txt
followthemoney_enrich-2.9.7.dist-info/namespace_packages.txt
followthemoney_enrich-2.9.7.dist-info/top_level.txt
followthemoney_enrich-2.9.7.dist-info/RECORD
