Metadata-Version: 2.1
Name: followthemoney-enrich
Version: 2.9.7
Summary: UNKNOWN
Home-page: https://occrp.org
Author: OCCRP
Author-email: data@occrp.org
License: MIT
Platform: UNKNOWN
Classifier: Development Status :: 3 - Alpha
Classifier: Intended Audience :: Developers
Classifier: Operating System :: OS Independent
Classifier: Programming Language :: Python
License-File: LICENSE
Requires-Dist: followthemoney
Requires-Dist: alephclient
Requires-Dist: requests
Requires-Dist: redis
